jezdzenka/__init__.py
jezdzenka/__main__.py
jezdzenka/application.py
jezdzenka/translation.py
jezdzenka/classes/DateTimeSerializer.py
jezdzenka/classes/Pkpass.py
jezdzenka/classes/Type.py
jezdzenka/classes/TypeSerializer.py
jezdzenka/console/controllers.py
jezdzenka/console/forms.py
jezdzenka/console/interface.py
jezdzenka/console/shows.py
jezdzenka/console/tables.py
jezdzenka/database/collection.py
jezdzenka/database/manipulation.py
jezdzenka/locale/en_US/LC_MESSAGES/base.mo
jezdzenka-1.5.dist-info/METADATA
jezdzenka-1.5.dist-info/WHEEL
jezdzenka-1.5.dist-info/entry_points.txt
jezdzenka-1.5.dist-info/top_level.txt
jezdzenka-1.5.dist-info/RECORD
